{
	//uview
	"easycom": {
		"^u-(.*)": "@/uni_modules/uview-ui/components/u-$1/u-$1.vue"
	},
	"pages": [{
		"path": "pages/login/login",
		"style": {
			"navigationStyle": "custom",
			"app-plus": {
				"animationType": "fade-in", // 设置fade-in淡入动画，为最合理的动画类型
				"background": "transparent", // 背景透明
				"backgroundColor": "rgba(0,0,0,0)", // 背景透明
				"popGesture": "none" // 关闭IOS屏幕左边滑动关闭当前页面的功能
			}
		}
	}, {
		"path": "pages/mobilelogin/mobilelogin",
		"style": {
			"navigationStyle": "custom"
		}
	}, {
		"path": "pages/reg/reg",
		"style": {
			"navigationStyle": "custom"
		}
	}, {
		"path": "pages/index/index",
		"style": {
			"navigationStyle": "custom",
			"enablePullDownRefresh": true,
			"app-plus": {
					"animationType": "slide-in-right",
					"animationDuration": 300
				}
		}
	}, {
		"path": "pages/shop/shop",
		"style": {
			"navigationStyle": "custom",
			"app-plus": {
					"animationType": "slide-in-right",
					"animationDuration": 300
				}
		}
	}, {
		"path": "pages/shop/ItemDetail",
		"style": {
			"navigationStyle": "custom"
		}
	},{
		"path": "pages/shop/shoppingcart",
		"style": {
			"navigationStyle": "custom"
		}
	}, {
		"path": "pages/dongtai/dongtai",
		"style": {
			"navigationStyle": "custom",
			"app-plus": {
					"animationType": "slide-in-right",
					"animationDuration": 300
				}
		}
	}, {
		"path": "pages/my/my",
		"style": {
			"navigationStyle": "custom",
			"app-plus": {
					"animationType": "slide-in-right",
					"animationDuration": 300
				}
		}
	}, {
		"path": "pages/add/add",
		"style": {
			"navigationStyle": "custom",
			"app-plus": {
					"animationType": "slide-in-right",
					"animationDuration": 300
				}
		}
	}, {
		"path": "pages/setting/setting",
		"style": {
			"navigationStyle": "custom",
			// "navigationStyle": "设置",
			"navigationBarTextStyle": "white"
			// "navigationBarTitleText": "设置",
			// "navigationBarBackgroundColor": "#ff9bb9"
		}
	}, {
		"path": "pages/video/video",
		"style": {
			"navigationStyle": "custom"
		}
	},{
		"path": "pages/demo/demo",
		"style": {
			"navigationStyle": "custom",
			"enablePullDownRefresh": true
		}
	},{
		"path": "pages/shop/orders",
		"style": {
			"navigationStyle": "custom"
		}
	},{
		"path": "pages/shop/Toaddr",
		"style": {
			"navigationStyle": "custom"
		}
	},{
		"path": "pages/shop/addSite",
		"style": {
			"navigationStyle": "custom"
		}
	}],
	"globalStyle": {
		"enablePullDownRefresh": false,
		"onReachBottomDistance": 50
	},
	"tabBar": {
		"selectedColor": "#ff9bb9",
		"list": [{
				"pagePath": "pages/index/index",
				"text": "首页",
				"iconPath": "./static/tabbar/gitlab.png",
				"selectedIconPath": "./static/tabbar/gitlab-select.png"
			}, {
				"pagePath": "pages/shop/shop",
				"text": "会员购",
				"iconPath": "./static/tabbar/wind.png",
				"selectedIconPath": "./static/tabbar/wind-select.png"
			}, {
				"pagePath": "pages/add/add",
				// "text": "添加",
				"iconPath": "./static/tabbar/add.png",
				"selectedIconPath": "./static/tabbar/add.png"
			},
			{
				"pagePath": "pages/dongtai/dongtai",
				"text": "动态",
				"iconPath": "./static/tabbar/friend.png",
				"selectedIconPath": "./static/tabbar/friend-select.png"
			}, {
				"pagePath": "pages/my/my",
				"text": "我的",
				"iconPath": "./static/tabbar/tv.png",
				"selectedIconPath": "./static/tabbar/tv-select.png"
			}
		]
	}
}